synology_office_exporter/__init__.py
synology_office_exporter/__main__.py
synology_office_exporter/_version.py
synology_office_exporter/cli.py
synology_office_exporter/download_history.py
synology_office_exporter/exception.py
synology_office_exporter/exporter.py
synology_office_exporter/synology_drive_api.py
synology_office_exporter-0.0.9.dist-info/licenses/LICENSE
synology_office_exporter-0.0.9.dist-info/METADATA
synology_office_exporter-0.0.9.dist-info/WHEEL
synology_office_exporter-0.0.9.dist-info/entry_points.txt
synology_office_exporter-0.0.9.dist-info/top_level.txt
synology_office_exporter-0.0.9.dist-info/RECORD
