Metadata-Version: 2.4
Name: synology-office-exporter
Version: 0.0.9
Summary: Tools for exporting Synology Office files from Synology NAS devices
Author: Issei Suzuki
Project-URL: Homepage, https://github.com/isseis/synology-office-exporter
Project-URL: Bug Tracker, https://github.com/isseis/synology-office-exporter/issues
Keywords: synology,office,exporter
Classifier: Programming Language :: Python :: 3.6
Classifier: Operating System :: OS Independent
Classifier: Development Status :: 3 - Alpha
Requires-Python: >=3.6
License-File: LICENSE
Requires-Dist: filelock>=3.18.0
Requires-Dist: python-dotenv>=0.19.0
Requires-Dist: synology-drive-api>=1.0.15
Requires-Dist: typing-extensions>=4.12.0
Requires-Dist: urllib3<2.0.0
Provides-Extra: dev
Requires-Dist: autopep8; extra == "dev"
Requires-Dist: flake8; extra == "dev"
Requires-Dist: flake8-quotes; extra == "dev"
Requires-Dist: build; extra == "dev"
Requires-Dist: twine; extra == "dev"
Requires-Dist: flake8>=7.1.2; extra == "dev"
Requires-Dist: coverage>=7.0.0; extra == "dev"
Requires-Dist: pre-commit>=2.15.0; extra == "dev"
Dynamic: license-file
